chronous/Architecture.py
chronous/__init__.py
chronous/events/Event.py
chronous/events/LifecycleEvents.py
chronous/events/__init__.py
chronous/sample/Sample.py
chronous/sample/__init__.py
chronous-1.2.1.dist-info/LICENSE
chronous-1.2.1.dist-info/METADATA
chronous-1.2.1.dist-info/WHEEL
chronous-1.2.1.dist-info/top_level.txt
chronous-1.2.1.dist-info/RECORD
